README.md
setup.py
pm/__init__.py
pm/controller.py
pm/charts/__init__.py
pm/charts/bugs.py
pm/charts/genie.py
pm/charts/melon.py
power_music.egg-info/PKG-INFO
power_music.egg-info/SOURCES.txt
power_music.egg-info/dependency_links.txt
power_music.egg-info/requires.txt
power_music.egg-info/top_level.txt
tests/__init__.py
tests/test_convert.py