Metadata-Version: 2.1
Name: power-music
Version: 0.0.0.1
Summary: Convert music site charts to youtube links
Home-page: https://github.com/dart-bird/power-music
Author: DartBird
Author-email: jintechdevel@gmail.com
License: UNKNOWN
Platform: UNKNOWN
Classifier: Programming Language :: Python :: 3
Classifier: License :: OSI Approved :: MIT License
Classifier: Operating System :: OS Independent
Requires-Python: >=3.6
